read_cheque/__init__.py
readchequeutility/__init__.py
readchequeutility-0.0.2.dist-info/LICENCE.txt
readchequeutility-0.0.2.dist-info/METADATA
readchequeutility-0.0.2.dist-info/WHEEL
readchequeutility-0.0.2.dist-info/top_level.txt
readchequeutility-0.0.2.dist-info/RECORD
